vizura/Vizura.py
vizura/__init__.py
vizura/streamlit_app.py
vizura-0.1.23.dist-info/LICENSE
vizura-0.1.23.dist-info/METADATA
vizura-0.1.23.dist-info/WHEEL
vizura-0.1.23.dist-info/top_level.txt
vizura-0.1.23.dist-info/RECORD
