Metadata-Version: 2.1
Name: vizura
Version: 0.1.23
Summary: Tool for Data Analysis
Author: Aswath Shakthi
Author-email: aswathshakthi@outlook.com
Project-URL: Demo, https://vizura.streamlit.app
Project-URL: Source, https://github.com/ash-sha/vizura
Classifier: Programming Language :: Python :: 3
Classifier: License :: OSI Approved :: MIT License
Classifier: Operating System :: OS Independent
Classifier: Intended Audience :: Developers
Classifier: Intended Audience :: Science/Research
Requires-Python: >=3.6
License-File: LICENSE
Requires-Dist: dash
Requires-Dist: dash_bootstrap_components
Requires-Dist: dash_core_components
Requires-Dist: dash_html_components
Requires-Dist: matplotlib
Requires-Dist: numpy
Requires-Dist: pandas
Requires-Dist: plotly
Requires-Dist: scikit_learn
Requires-Dist: scipy
Requires-Dist: seaborn
Requires-Dist: setuptools>=70.0.0
Requires-Dist: streamlit
